encoda/__init__.py
encoda/encod26.py
encod26-0.0.1.dist-info/METADATA
encod26-0.0.1.dist-info/WHEEL
encod26-0.0.1.dist-info/top_level.txt
encod26-0.0.1.dist-info/RECORD
