Metadata-Version: 2.1
Name: encod26
Version: 0.0.1
Summary: String encoder
Home-page: UNKNOWN
Author: Aryan Katiyar
Author-email: aryankatiyar1420@gmail.com
License: UNKNOWN
Keywords: python,encoder,string,password
Platform: UNKNOWN
Classifier: Development Status :: 1 - Planning
Classifier: Intended Audience :: Developers
Classifier: Programming Language :: Python :: 3
Classifier: Operating System :: Unix
Classifier: Operating System :: MacOS :: MacOS X
Classifier: Operating System :: Microsoft :: Windows
Requires-Dist: hashlib
